ozon_seller/__init__.py
ozon_seller/actions.py
ozon_seller/actions_candidates.py
ozon_seller/actions_products.py
ozon_seller/chat_send_message.py
ozon_seller/chat_start.py
ozon_seller/fbs_act_get_postings.py
ozon_seller/posting_fbo_list.py
ozon_seller/posting_fbs_act_check_status.py
ozon_seller/posting_fbs_act_create.py
ozon_seller/posting_fbs_act_get_barcode.py
ozon_seller/posting_fbs_get.py
ozon_seller/posting_fbs_list.py
ozon_seller/posting_fbs_package_label.py
ozon_seller/posting_fbs_product_country_list.py
ozon_seller/posting_fbs_product_country_set.py
ozon_seller/posting_fbs_ship_gtd.py
ozon_seller/product_description.py
ozon_seller/product_import_prices.py
ozon_seller/product_import_stocks.py
ozon_seller/product_info.py
ozon_seller/product_info_attributes.py
ozon_seller/product_pictures_import.py
ozon_seller/products_stocks.py
ozon_seller/returns_fbo.py
ozon_seller/returns_fbs.py
ozon_seller/stocks.py
ozon_seller/common/__init__.py
ozon_seller/common/credentials.py
ozon_seller/common/data_class_json_mixin.py
ozon_seller/common/datetime_field.py
ozon_seller/common/error_response.py
ozon_seller/common/http_error.py
ozon_seller/common/make_iterative.py
ozon_seller/common/renamed_field.py
ozon_seller/common/request_api.py
ozon_seller/tests/__init__.py
ozon_seller/tests/base_test_case.py
ozon_seller/tests/common.py
ozon_seller/tests/integration_test.py
ozon_seller/tests/integration_test_case.py
ozon_seller/tests/load_test_case.py
ozon_seller/tests/qualified_name.py
ozon_seller/tests/requests_test.py
ozon_seller/tests/responses_test.py
ozon_seller/tests/test_server.py
ozon_seller/tests/test_server_endpoint.py
ozon_seller/tests/test_server_handler.py
ozon_seller-1.0.0.dist-info/licenses/LICENSE.txt
ozon_seller-1.0.0.dist-info/METADATA
ozon_seller-1.0.0.dist-info/WHEEL
ozon_seller-1.0.0.dist-info/top_level.txt
ozon_seller-1.0.0.dist-info/RECORD
