Metadata-Version: 2.4
Name: ozon-seller
Version: 1.0.0
Summary: Ozon seller library
Author-email: irenica <root@irenica.pro>
License-Expression: MIT
Project-URL: repository, https://github.com/irenicaa/ozon-seller
Requires-Python: <4.0.0,>=3.9.13
License-File: LICENSE.txt
Requires-Dist: dataclasses_json<1.0.0,>=0.5.7
Requires-Dist: marshmallow<4.0.0,>=3.16.0
Requires-Dist: requests<3.0.0,>=2.28.0
Dynamic: license-file
